setup.py
comicfetcher/command_line.py
comicfetcher.egg-info/PKG-INFO
comicfetcher.egg-info/SOURCES.txt
comicfetcher.egg-info/dependency_links.txt
comicfetcher.egg-info/entry_points.txt
comicfetcher.egg-info/requires.txt
comicfetcher.egg-info/top_level.txt