Metadata-Version: 1.0
Name: comicfetcher
Version: 0.3
Summary: Lets you fetch memes and comics
Home-page: https://github.com/lakshaykalbhor/comic-fetcher
Author: Lakshay Kalbhor
Author-email: lakshaykalbhor@gmail.com
License: MIT
Platform: UNKNOWN
